pyquoks/__init__.py
pyquoks/data.py
pyquoks/localhost.py
pyquoks/test.py
pyquoks/utils.py
pyquoks-2.3.0.dist-info/licenses/LICENSE
pyquoks-2.3.0.dist-info/METADATA
pyquoks-2.3.0.dist-info/WHEEL
pyquoks-2.3.0.dist-info/RECORD
