Metadata-Version: 2.4
Name: pyquoks
Version: 2.3.0
Summary: Пакет PyPI для часто используемых модулей в проектах diquoks
License: MIT
License-File: LICENSE
Author: Denis Titovets
Author-email: den232titovets@yandex.ru
Requires-Python: >=3.14
Classifier: License :: OSI Approved :: MIT License
Classifier: Programming Language :: Python :: 3
Classifier: Programming Language :: Python :: 3.14
Requires-Dist: annotated-types (==0.7.0)
Requires-Dist: blinker (==1.9.0)
Requires-Dist: certifi (==2025.11.12)
Requires-Dist: charset-normalizer (==3.4.4)
Requires-Dist: click (==8.3.1)
Requires-Dist: colorama (==0.4.6)
Requires-Dist: flask (==3.1.2)
Requires-Dist: idna (==3.11)
Requires-Dist: itsdangerous (==2.2.0)
Requires-Dist: jinja2 (==3.1.6)
Requires-Dist: markupsafe (==3.0.3)
Requires-Dist: pillow (==12.0.0)
Requires-Dist: psutil (==7.2.1)
Requires-Dist: pydantic (==2.12.5)
Requires-Dist: pydantic-core (==2.41.5)
Requires-Dist: requests (==2.32.5)
Requires-Dist: typing-extensions (==4.15.0)
Requires-Dist: typing-inspection (==0.4.2)
Requires-Dist: urllib3 (==2.6.2)
Requires-Dist: waitress (==3.0.2)
Requires-Dist: werkzeug (==3.1.4)
